[
  {
    "Type": "BlueprintGeneratedClass",
    "Name": "PS_Lox_Chef_Neutral_C",
    "Class": "UScriptClass'BlueprintGeneratedClass'",
    "Flags": "RF_Public | RF_Transactional | RF_WasLoaded | RF_LoadCompleted",
    "SuperStruct": {
      "ObjectName": "Class'RivalsColorPalette'",
      "ObjectPath": "/Script/Rivals2"
    },
    "ClassFlags": "CLASS_ReplicationDataIsSetUp | CLASS_CompiledFromBlueprint",
    "ClassWithin": {
      "ObjectName": "Class'Object'",
      "ObjectPath": "/Script/CoreUObject"
    },
    "ClassConfigName": "Engine",
    "bCooked": true,
    "ClassDefaultObject": {
      "ObjectName": "PS_Lox_Chef_Neutral_C'Default__PS_Lox_Chef_Neutral_C'",
      "ObjectPath": "Rivals2/Content/Characters/Loxodont/Skins/Chef/Data/Palettes/Neutral/PS_Lox_Chef_Neutral.1"
    },
    "EditorTags": {
      "BlueprintType": "BPTYPE_Normal"
    }
  },
  {
    "Type": "PS_Lox_Chef_Neutral_C",
    "Name": "Default__PS_Lox_Chef_Neutral_C",
    "Class": "BlueprintGeneratedClass'Rivals2/Content/Characters/Loxodont/Skins/Chef/Data/Palettes/Neutral/PS_Lox_Chef_Neutral.PS_Lox_Chef_Neutral_C'",
    "Flags": "RF_Public | RF_ClassDefaultObject | RF_ArchetypeObject | RF_WasLoaded | RF_LoadCompleted",
    "Properties": {
      "CustomColorSlotDefinitions": [
        {
          "Key": "Shirt",
          "Name": "Shirt",
          "Value": {
            "R": 0.379,
            "G": 0.346027,
            "B": 0.346027,
            "A": 1.0,
            "Hex": "A69F9F"
          }
        },
        {
          "Key": "Pants",
          "Name": "Pants",
          "Value": {
            "R": 0.03,
            "G": 0.022616,
            "B": 0.024943,
            "A": 1.0,
            "Hex": "30292B"
          }
        },
        {
          "Key": "Apron",
          "Name": "Apron",
          "Value": {
            "R": 0.329,
            "G": 0.024287,
            "B": 0.023222,
            "A": 1.0,
            "Hex": "9B2B2A"
          }
        },
        {
          "Key": "Mustache",
          "Name": "Mustache",
          "Value": {
            "R": 0.03,
            "G": 0.01887,
            "B": 0.01887,
            "A": 1.0,
            "Hex": "302525"
          }
        },
        {
          "Key": "ShirtM",
          "Name": "ShirtM",
          "Value": {
            "R": 0.283149,
            "G": 0.144128,
            "B": 0.144128,
            "A": 1.0,
            "Hex": "916A6A"
          }
        },
        {
          "Key": "Sauce",
          "Name": "Sauce",
          "Value": {
            "R": 0.135633,
            "G": 0.015996,
            "B": 0.008568,
            "A": 1.0,
            "Hex": "672217"
          }
        },
        {
          "Key": "Pasta",
          "Name": "Pasta",
          "Value": {
            "R": 0.366253,
            "G": 0.181164,
            "B": 0.0865,
            "A": 1.0,
            "Hex": "A37653"
          }
        },
        {
          "Key": "Wood",
          "Name": "Wood",
          "Value": {
            "R": 0.289,
            "G": 0.150473,
            "B": 0.076874,
            "A": 1.0,
            "Hex": "926C4E"
          }
        },
        {
          "Key": "Meatball",
          "Name": "Meatball",
          "Value": {
            "R": 0.093059,
            "G": 0.03434,
            "B": 0.028426,
            "A": 1.0,
            "Hex": "56342F"
          }
        },
        {
          "Key": "Parsley",
          "Name": "Parsley",
          "Value": {
            "R": 0.004391,
            "G": 0.093059,
            "B": 0.007499,
            "A": 1.0,
            "Hex": "0E5615"
          }
        },
        {
          "Key": "Brick1",
          "Name": "Brick1",
          "Value": {
            "R": 0.198069,
            "G": 0.029557,
            "B": 0.027321,
            "A": 1.0,
            "Hex": "7B302E"
          }
        },
        {
          "Key": "Brick2",
          "Name": "Brick2",
          "Value": {
            "R": 0.23074,
            "G": 0.056128,
            "B": 0.040915,
            "A": 1.0,
            "Hex": "844339"
          }
        },
        {
          "Key": "Brick3",
          "Name": "Brick3",
          "Value": {
            "R": 0.162029,
            "G": 0.040915,
            "B": 0.038204,
            "A": 1.0,
            "Hex": "703937"
          }
        },
        {
          "Key": "Metal",
          "Name": "Metal",
          "Value": {
            "R": 0.072272,
            "G": 0.042311,
            "B": 0.040915,
            "A": 1.0,
            "Hex": "4C3A39"
          }
        },
        {
          "Key": "Cement",
          "Name": "Cement",
          "Value": {
            "R": 0.250158,
            "G": 0.141263,
            "B": 0.122139,
            "A": 1.0,
            "Hex": "896962"
          }
        },
        {
          "Key": "Body",
          "Name": "Body",
          "Value": {
            "R": 0.191202,
            "G": 0.191202,
            "B": 0.187821,
            "A": 1.0,
            "Hex": "797978"
          }
        },
        {
          "Key": "Scars",
          "Name": "Scars",
          "Value": {
            "R": 0.315,
            "G": 0.315,
            "B": 0.30943,
            "A": 1.0,
            "Hex": "989897"
          }
        },
        {
          "Key": "Nails",
          "Name": "Nails",
          "Value": {
            "R": 0.223,
            "G": 0.223,
            "B": 0.223,
            "A": 1.0,
            "Hex": "828282"
          }
        },
        {
          "Key": "Pupil",
          "Name": "Pupil",
          "Value": {
            "R": 0.394,
            "G": 0.15457,
            "B": 0.014184,
            "A": 1.0,
            "Hex": "A96D1F"
          }
        },
        {
          "Key": "Scelera",
          "Name": "Scelera",
          "Value": {
            "R": 0.012,
            "G": 0.012,
            "B": 0.012,
            "A": 1.0,
            "Hex": "1C1C1C"
          }
        },
        {
          "Key": "Tusks",
          "Name": "Tusks",
          "Value": {
            "R": 0.558,
            "G": 0.558,
            "B": 0.558,
            "A": 1.0,
            "Hex": "C5C5C5"
          }
        }
      ]
    }
  }
]