[
  {
    "Type": "BlueprintGeneratedClass",
    "Name": "PS_Fle_Pajama_Green_C",
    "Class": "UScriptClass'BlueprintGeneratedClass'",
    "Flags": "RF_Public | RF_Transactional | RF_WasLoaded | RF_LoadCompleted",
    "SuperStruct": {
      "ObjectName": "Class'RivalsColorPalette'",
      "ObjectPath": "/Script/Rivals2"
    },
    "ClassFlags": "CLASS_ReplicationDataIsSetUp | CLASS_CompiledFromBlueprint",
    "ClassWithin": {
      "ObjectName": "Class'Object'",
      "ObjectPath": "/Script/CoreUObject"
    },
    "ClassConfigName": "Engine",
    "bCooked": true,
    "ClassDefaultObject": {
      "ObjectName": "PS_Fle_Pajama_Green_C'Default__PS_Fle_Pajama_Green_C'",
      "ObjectPath": "Rivals2/Content/Characters/Fleet/Skins/Pyjama/Data/Palettes/Green/PS_Fle_Pajama_Green.1"
    },
    "EditorTags": {
      "BlueprintType": "BPTYPE_Normal"
    }
  },
  {
    "Type": "PS_Fle_Pajama_Green_C",
    "Name": "Default__PS_Fle_Pajama_Green_C",
    "Class": "BlueprintGeneratedClass'Rivals2/Content/Characters/Fleet/Skins/Pyjama/Data/Palettes/Green/PS_Fle_Pajama_Green.PS_Fle_Pajama_Green_C'",
    "Flags": "RF_Public | RF_Transactional | RF_ClassDefaultObject | RF_ArchetypeObject | RF_WasLoaded | RF_LoadCompleted",
    "Properties": {
      "CustomColorSlotDefinitions": [
        {
          "Key": "Cape",
          "Name": "Cape",
          "Value": {
            "R": 0.201287,
            "G": 0.085639,
            "B": 0.401042,
            "A": 1.0,
            "Hex": "7C52AA"
          }
        },
        {
          "Key": "CapeTrim",
          "Name": "CapeTrim",
          "Value": {
            "R": 0.609375,
            "G": 0.609375,
            "B": 0.609375,
            "A": 1.0,
            "Hex": "CDCDCD"
          }
        },
        {
          "Key": "Accent",
          "Name": "Accent",
          "Value": {
            "R": 0.734375,
            "G": 0.246449,
            "B": 0.053548,
            "A": 1.0,
            "Hex": "DF8841"
          }
        },
        {
          "Key": "ClothingTrim",
          "Name": "ClothingTrim",
          "Value": {
            "R": 0.770833,
            "G": 0.561797,
            "B": 0.200738,
            "A": 1.0,
            "Hex": "E4C67C"
          }
        },
        {
          "Key": "Clothing",
          "Name": "Clothing",
          "Value": {
            "R": 0.260024,
            "G": 0.545724,
            "B": 0.082427,
            "A": 1.0,
            "Hex": "8CC351"
          }
        }
      ]
    }
  }
]