[
  {
    "Type": "BlueprintGeneratedClass",
    "Name": "PS_Fle_Badger_Red_C",
    "Class": "UScriptClass'BlueprintGeneratedClass'",
    "Flags": "RF_Public | RF_Transactional | RF_WasLoaded | RF_LoadCompleted",
    "SuperStruct": {
      "ObjectName": "Class'RivalsColorPalette'",
      "ObjectPath": "/Script/Rivals2"
    },
    "ClassFlags": "CLASS_ReplicationDataIsSetUp | CLASS_CompiledFromBlueprint",
    "ClassWithin": {
      "ObjectName": "Class'Object'",
      "ObjectPath": "/Script/CoreUObject"
    },
    "ClassConfigName": "Engine",
    "bCooked": true,
    "ClassDefaultObject": {
      "ObjectName": "PS_Fle_Badger_Red_C'Default__PS_Fle_Badger_Red_C'",
      "ObjectPath": "Rivals2/Content/Characters/Fleet/Skins/Badger/Data/Palettes/Red/PS_Fle_Badger_Red.1"
    },
    "EditorTags": {
      "BlueprintType": "BPTYPE_Normal"
    }
  },
  {
    "Type": "PS_Fle_Badger_Red_C",
    "Name": "Default__PS_Fle_Badger_Red_C",
    "Class": "BlueprintGeneratedClass'Rivals2/Content/Characters/Fleet/Skins/Badger/Data/Palettes/Red/PS_Fle_Badger_Red.PS_Fle_Badger_Red_C'",
    "Flags": "RF_Public | RF_ClassDefaultObject | RF_ArchetypeObject | RF_WasLoaded | RF_LoadCompleted",
    "Properties": {
      "CustomColorSlotDefinitions": [
        {
          "Key": "Body",
          "Name": "Body",
          "Value": {
            "R": 0.082283,
            "G": 0.037192,
            "B": 0.037192,
            "A": 1.0,
            "Hex": "513636"
          }
        },
        {
          "Key": "Belly",
          "Name": "Belly",
          "Value": {
            "R": 0.767,
            "G": 0.481881,
            "B": 0.349752,
            "A": 1.0,
            "Hex": "E3B9A0"
          }
        },
        {
          "Key": "Pattern",
          "Name": "Pattern",
          "Value": {
            "R": 0.027,
            "G": 0.012204,
            "B": 0.012204,
            "A": 1.0,
            "Hex": "2D1C1C"
          }
        },
        {
          "Key": "Paws",
          "Name": "Paws",
          "Value": {
            "R": 0.008,
            "G": 0.007432,
            "B": 0.007216,
            "A": 1.0,
            "Hex": "161414"
          }
        },
        {
          "Key": "Pants",
          "Name": "Pants",
          "Value": {
            "R": 0.136,
            "G": 0.072606,
            "B": 0.035904,
            "A": 1.0,
            "Hex": "674C35"
          }
        },
        {
          "Key": "Shirt",
          "Name": "Shirt",
          "Value": {
            "R": 0.331,
            "G": 0.021515,
            "B": 0.021515,
            "A": 1.0,
            "Hex": "9C2828"
          }
        },
        {
          "Key": "Shirt2",
          "Name": "Shirt2",
          "Value": {
            "R": 0.502,
            "G": 0.17821,
            "B": 0.17821,
            "A": 1.0,
            "Hex": "BC7575"
          }
        },
        {
          "Key": "Belts",
          "Name": "Belts",
          "Value": {
            "R": 0.136,
            "G": 0.044381,
            "B": 0.01904,
            "A": 1.0,
            "Hex": "673B25"
          }
        },
        {
          "Key": "Cape",
          "Name": "Cape",
          "Value": {
            "R": 0.576,
            "G": 0.160128,
            "B": 0.160128,
            "A": 1.0,
            "Hex": "C86F6F"
          }
        },
        {
          "Key": "CapeTrim",
          "Name": "CapeTrim",
          "Value": {
            "R": 0.331,
            "G": 0.021515,
            "B": 0.021515,
            "A": 1.0,
            "Hex": "9C2828"
          }
        },
        {
          "Key": "BowWraps",
          "Name": "BowWraps",
          "Value": {
            "R": 0.5,
            "G": 0.35,
            "B": 0.35,
            "A": 1.0,
            "Hex": "BCA0A0"
          }
        },
        {
          "Key": "BowGem",
          "Name": "BowGem",
          "Value": {
            "R": 1.0,
            "G": 0.03,
            "B": 0.143166,
            "A": 1.0,
            "Hex": "FF306A"
          }
        },
        {
          "Key": "Wood",
          "Name": "Wood",
          "Value": {
            "R": 0.332452,
            "G": 0.102242,
            "B": 0.057805,
            "A": 1.0,
            "Hex": "9C5A44"
          }
        },
        {
          "Key": "Bow",
          "Name": "Bow",
          "Value": {
            "R": 0.331,
            "G": 0.021515,
            "B": 0.021515,
            "A": 1.0,
            "Hex": "9C2828"
          }
        },
        {
          "Key": "BowMetal",
          "Name": "BowMetal",
          "Value": {
            "R": 0.25,
            "G": 0.12225,
            "B": 0.12225,
            "A": 1.0,
            "Hex": "896262"
          }
        },
        {
          "Key": "Eyes",
          "Name": "Eyes",
          "Value": {
            "R": 0.002355,
            "G": 0.440177,
            "B": 0.878,
            "A": 1.0,
            "Hex": "07B1F1"
          }
        }
      ]
    }
  }
]